jaxsne/__init__.py
jaxsne/_measure.py
jaxsne/_metric.py
jaxsne/_scaling.py
jaxsne/_sne.py
jaxsne/_utils.py
jaxsne/measure.py
jaxsne/metric.py
jaxsne/py.typed
jaxsne-0.2.0.dist-info/METADATA
jaxsne-0.2.0.dist-info/WHEEL
jaxsne-0.2.0.dist-info/licenses/LICENSE
jaxsne-0.2.0.dist-info/RECORD
