Metadata-Version: 2.4
Name: jaxsne
Version: 0.2.0
Summary: A library for doing dimensionality reduction with different curvature
License-File: LICENSE
Keywords: cosine,distance,metric,sne,tsne
Requires-Python: >=3.10
Requires-Dist: jax>=0.5.1
Requires-Dist: numpy>=2.1.3
Requires-Dist: scipy>=1.15.2
